README.md
__init__.py
example.py
pubsub.py
school_backends.py
setup.py
test_pubnub_backend.py
test_pubsub.py
test_redis_backend.py
school_pubsub.egg-info/PKG-INFO
school_pubsub.egg-info/SOURCES.txt
school_pubsub.egg-info/dependency_links.txt
school_pubsub.egg-info/not-zip-safe
school_pubsub.egg-info/top_level.txt