Metadata-Version: 1.0
Name: school-pubsub
Version: 0.6.9
Summary: An abstracted interface for pub/sub between microservices
Home-page: https://github.com/AppointmentGuru/PubSubGuru
Author: Christo Crampton
Author-email: tech@appointmentguru.co
License: MIT
Platform: UNKNOWN
